hsBremerhaven/__init__.py
hsBremerhaven/hsBremerhaven.py
hs_bremerhaven/__init__.py
hs_bremerhaven/hs_bremerhaven.py
hsBremerhaven-0.0.1.dist-info/METADATA
hsBremerhaven-0.0.1.dist-info/WHEEL
hsBremerhaven-0.0.1.dist-info/top_level.txt
hsBremerhaven-0.0.1.dist-info/RECORD
